{
  "annotations": {
    "list": [
      {
        "builtIn": 1,
        "datasource": {
          "type": "datasource",
          "uid": "grafana"
        },
        "enable": true,
        "hide": true,
        "iconColor": "rgba(0, 211, 255, 1)",
        "name": "Annotations & Alerts",
        "target": {
          "limit": 100,
          "matchAny": false,
          "tags": [],
          "type": "dashboard"
        },
        "type": "dashboard"
      }
    ]
  },
  "editable": true,
  "fiscalYearStartMonth": 0,
  "graphTooltip": 0,
  "links": [],
  "liveNow": false,
  "panels": [
    {
      "datasource": {
        "type": "prometheus",
        "uid": "PBFA97CFB590B2093"
      },
      "gridPos": {
        "h": 5,
        "w": 6,
        "x": 0,
        "y": 0
      },
      "id": 2,
      "options": {
        "content": "<div>\n  <img width=\"100\" height=\"100\" src=\"https://logosandtypes.com/wp-content/uploads/2020/12/altinity.svg\"/>\n<p>Altinity Sink Connector for ClickHouse</p>\n<p>For more information, visit <href https://github.com/Altinity/clickhouse-sink-connector\n</div>",
        "mode": "html"
      },
      "pluginVersion": "9.0.4",
      "targets": [
        {
          "datasource": {
            "type": "prometheus",
            "uid": "PBFA97CFB590B2093"
          },
          "refId": "A"
        }
      ],
      "title": "Altinity Sink Connector for ClickHouse",
      "type": "text"
    },
    {
      "datasource": {},
      "fieldConfig": {
        "defaults": {
          "color": {
            "mode": "thresholds"
          },
          "mappings": [],
          "thresholds": {
            "mode": "absolute",
            "steps": [
              {
                "color": "green",
                "value": null
              },
              {
                "color": "red",
                "value": 80
              }
            ]
          }
        },
        "overrides": []
      },
      "gridPos": {
        "h": 5,
        "w": 5,
        "x": 6,
        "y": 0
      },
      "id": 4,
      "options": {
        "colorMode": "value",
        "graphMode": "none",
        "justifyMode": "auto",
        "orientation": "auto",
        "reduceOptions": {
          "calcs": [
            "lastNotNull"
          ],
          "fields": "",
          "values": false
        },
        "text": {},
        "textMode": "auto"
      },
      "pluginVersion": "9.0.4",
      "targets": [
        {
          "datasource": {
            "uid": "prometheus"
          },
          "editorMode": "code",
          "exemplar": true,
          "expr": "clickhouse_sink_binlog_pos{}",
          "interval": "",
          "legendFormat": "",
          "range": true,
          "refId": "A"
        }
      ],
      "title": "Bin Log position",
      "type": "stat"
    },
    {
      "datasource": {},
      "fieldConfig": {
        "defaults": {
          "color": {
            "mode": "thresholds"
          },
          "mappings": [],
          "thresholds": {
            "mode": "absolute",
            "steps": [
              {
                "color": "green",
                "value": null
              },
              {
                "color": "red",
                "value": 80
              }
            ]
          }
        },
        "overrides": []
      },
      "gridPos": {
        "h": 5,
        "w": 5,
        "x": 11,
        "y": 0
      },
      "id": 6,
      "options": {
        "colorMode": "value",
        "graphMode": "none",
        "justifyMode": "auto",
        "orientation": "auto",
        "reduceOptions": {
          "calcs": [
            "lastNotNull"
          ],
          "fields": "",
          "values": false
        },
        "text": {},
        "textMode": "auto"
      },
      "pluginVersion": "9.0.4",
      "targets": [
        {
          "datasource": {
            "uid": "prometheus"
          },
          "editorMode": "code",
          "exemplar": true,
          "expr": "clickhouse_sink_gtid{}",
          "interval": "",
          "legendFormat": "",
          "range": true,
          "refId": "A"
        }
      ],
      "title": "GTID - Transaction Id",
      "type": "stat"
    },
    {
      "datasource": {},
      "fieldConfig": {
        "defaults": {
          "color": {
            "mode": "thresholds"
          },
          "custom": {
            "align": "auto",
            "displayMode": "auto",
            "filterable": false,
            "inspect": false
          },
          "mappings": [],
          "thresholds": {
            "mode": "absolute",
            "steps": [
              {
                "color": "green",
                "value": null
              },
              {
                "color": "red",
                "value": 80
              }
            ]
          }
        },
        "overrides": [
          {
            "matcher": {
              "id": "byName",
              "options": "topic"
            },
            "properties": [
              {
                "id": "custom.width",
                "value": 324
              }
            ]
          },
          {
            "matcher": {
              "id": "byName",
              "options": "job"
            },
            "properties": [
              {
                "id": "custom.width",
                "value": 72
              }
            ]
          },
          {
            "matcher": {
              "id": "byName",
              "options": "instance"
            },
            "properties": [
              {
                "id": "custom.width",
                "value": 109
              }
            ]
          }
        ]
      },
      "gridPos": {
        "h": 8,
        "w": 12,
        "x": 0,
        "y": 5
      },
      "id": 8,
      "options": {
        "footer": {
          "fields": "",
          "reducer": [
            "sum"
          ],
          "show": false
        },
        "frameIndex": 0,
        "showHeader": true,
        "sortBy": []
      },
      "pluginVersion": "9.0.4",
      "targets": [
        {
          "datasource": {
            "uid": "prometheus"
          },
          "editorMode": "code",
          "exemplar": true,
          "expr": "clickhouse_topics_num_records_total{}",
          "format": "table",
          "instant": true,
          "interval": "",
          "legendFormat": "",
          "refId": "A"
        }
      ],
      "title": "Records (Topic)",
      "type": "table"
    },
    {
      "datasource": {},
      "description": "",
      "fieldConfig": {
        "defaults": {
          "color": {
            "mode": "palette-classic"
          },
          "custom": {
            "axisLabel": "",
            "axisPlacement": "auto",
            "barAlignment": 0,
            "drawStyle": "line",
            "fillOpacity": 0,
            "gradientMode": "none",
            "hideFrom": {
              "legend": false,
              "tooltip": false,
              "viz": false
            },
            "lineInterpolation": "stepAfter",
            "lineWidth": 1,
            "pointSize": 5,
            "scaleDistribution": {
              "type": "linear"
            },
            "showPoints": "auto",
            "spanNulls": false,
            "stacking": {
              "group": "A",
              "mode": "none"
            },
            "thresholdsStyle": {
              "mode": "off"
            }
          },
          "mappings": [],
          "thresholds": {
            "mode": "absolute",
            "steps": [
              {
                "color": "green",
                "value": null
              },
              {
                "color": "red",
                "value": 80
              }
            ]
          }
        },
        "overrides": []
      },
      "gridPos": {
        "h": 8,
        "w": 12,
        "x": 12,
        "y": 5
      },
      "id": 10,
      "options": {
        "legend": {
          "calcs": [],
          "displayMode": "list",
          "placement": "bottom",
          "showLegend": true
        },
        "tooltip": {
          "mode": "single",
          "sort": "none"
        }
      },
      "targets": [
        {
          "datasource": {
            "uid": "prometheus"
          },
          "editorMode": "code",
          "exemplar": true,
          "expr": "clickhouse_topics_num_records_total{}",
          "interval": "",
          "legendFormat": "",
          "range": true,
          "refId": "A"
        }
      ],
      "title": "Total Records",
      "type": "timeseries"
    },
    {
      "datasource": {},
      "fieldConfig": {
        "defaults": {
          "color": {
            "mode": "palette-classic"
          },
          "custom": {
            "axisLabel": "",
            "axisPlacement": "auto",
            "barAlignment": 0,
            "drawStyle": "line",
            "fillOpacity": 0,
            "gradientMode": "none",
            "hideFrom": {
              "legend": false,
              "tooltip": false,
              "viz": false
            },
            "lineInterpolation": "linear",
            "lineWidth": 1,
            "pointSize": 5,
            "scaleDistribution": {
              "type": "linear"
            },
            "showPoints": "auto",
            "spanNulls": false,
            "stacking": {
              "group": "A",
              "mode": "none"
            },
            "thresholdsStyle": {
              "mode": "off"
            }
          },
          "mappings": [],
          "thresholds": {
            "mode": "absolute",
            "steps": [
              {
                "color": "green",
                "value": null
              },
              {
                "color": "red",
                "value": 80
              }
            ]
          }
        },
        "overrides": []
      },
      "gridPos": {
        "h": 8,
        "w": 12,
        "x": 0,
        "y": 13
      },
      "id": 12,
      "options": {
        "legend": {
          "calcs": [],
          "displayMode": "list",
          "placement": "bottom",
          "showLegend": true
        },
        "tooltip": {
          "mode": "single",
          "sort": "none"
        }
      },
      "targets": [
        {
          "datasource": {
            "uid": "prometheus"
          },
          "editorMode": "code",
          "exemplar": true,
          "expr": "clickhouse_sink_partition_offset{}",
          "interval": "",
          "legendFormat": "",
          "range": true,
          "refId": "A"
        }
      ],
      "title": "Kafka Offset",
      "type": "timeseries"
    },
    {
      "datasource": {},
      "description": "Lag calculated from time records are inserted to CH and the timestamp recorded by debezium connector",
      "fieldConfig": {
        "defaults": {
          "color": {
            "mode": "palette-classic"
          },
          "custom": {
            "axisLabel": "",
            "axisPlacement": "auto",
            "barAlignment": 0,
            "drawStyle": "line",
            "fillOpacity": 0,
            "gradientMode": "none",
            "hideFrom": {
              "legend": false,
              "tooltip": false,
              "viz": false
            },
            "lineInterpolation": "linear",
            "lineWidth": 1,
            "pointSize": 5,
            "scaleDistribution": {
              "type": "linear"
            },
            "showPoints": "auto",
            "spanNulls": false,
            "stacking": {
              "group": "A",
              "mode": "none"
            },
            "thresholdsStyle": {
              "mode": "off"
            }
          },
          "mappings": [],
          "thresholds": {
            "mode": "absolute",
            "steps": [
              {
                "color": "green",
                "value": null
              },
              {
                "color": "red",
                "value": 80
              }
            ]
          }
        },
        "overrides": []
      },
      "gridPos": {
        "h": 8,
        "w": 12,
        "x": 12,
        "y": 13
      },
      "id": 14,
      "options": {
        "legend": {
          "calcs": [],
          "displayMode": "list",
          "placement": "bottom",
          "showLegend": true
        },
        "tooltip": {
          "mode": "single",
          "sort": "none"
        }
      },
      "targets": [
        {
          "datasource": {
            "type": "prometheus",
            "uid": "PBFA97CFB590B2093"
          },
          "editorMode": "code",
          "expr": "clickhouse_sink_lag",
          "legendFormat": "__auto",
          "range": true,
          "refId": "A"
        }
      ],
      "title": "Sink Connector Lag",
      "type": "timeseries"
    }
  ],
  "refresh": false,
  "schemaVersion": 36,
  "style": "dark",
  "tags": [],
  "templating": {
    "list": []
  },
  "time": {
    "from": "now-5m",
    "to": "now"
  },
  "timepicker": {},
  "timezone": "",
  "title": "Altinity Sink Connector for ClickHouse",
  "uid": "c4cKtgk4k",
  "version": 1,
  "weekStart": ""
}